biliarchiver/_biliarchiver_upload_bvid.py
biliarchiver/archive_bvid.py
biliarchiver/cli_tools/bili_archive_bvids.py
biliarchiver/cli_tools/biliarchiver.py
biliarchiver/cli_tools/clean_command.py
biliarchiver/cli_tools/conf_command.py
biliarchiver/cli_tools/down_command.py
biliarchiver/cli_tools/get_command.py
biliarchiver/cli_tools/up_command.py
biliarchiver/cli_tools/utils.py
biliarchiver/config.py
biliarchiver/exception.py
biliarchiver/i18n.py
biliarchiver/locales/.gitignore
biliarchiver/locales/biliarchiver.pot
biliarchiver/locales/en/LC_MESSAGES/biliarchiver.mo
biliarchiver/locales/en/LC_MESSAGES/biliarchiver.po
biliarchiver/locales/en/LC_MESSAGES/biliarchiver.po~
biliarchiver/rest_api/bilivid.py
biliarchiver/rest_api/main.py
biliarchiver/utils/dirLock.py
biliarchiver/utils/ffmpeg.py
biliarchiver/utils/http_patch.py
biliarchiver/utils/identifier.py
biliarchiver/utils/storage.py
biliarchiver/utils/version_check.py
biliarchiver/utils/xml_chars.py
biliarchiver/version.py
biliarchiver-0.1.20.dist-info/LICENSE
biliarchiver-0.1.20.dist-info/METADATA
biliarchiver-0.1.20.dist-info/WHEEL
biliarchiver-0.1.20.dist-info/entry_points.txt
biliarchiver-0.1.20.dist-info/RECORD
