Metadata-Version: 2.1
Name: biliarchiver
Version: 0.1.20
Summary: Archiving tool for Bilibili based on bilix
Author: yzqzss
Author-email: yzqzss@yandex.com
Requires-Python: >=3.9,<4.0
Classifier: Programming Language :: Python :: 3
Classifier: Programming Language :: Python :: 3.9
Classifier: Programming Language :: Python :: 3.10
Classifier: Programming Language :: Python :: 3.11
Classifier: Programming Language :: Python :: 3.12
Classifier: Programming Language :: Python :: 3.13
Requires-Dist: bilix (==0.18.8)
Requires-Dist: browser-cookie3 (>=0.19.1,<0.20.0)
Requires-Dist: click (>=8.1.7,<9.0.0)
Requires-Dist: click-option-group (>=0.5.6,<0.6.0)
Requires-Dist: danmakuc (>=0.3.6,<0.4.0)
Requires-Dist: internetarchive (>=4.1.0,<5.0.0)
